bteve/__init__.py
bteve/_eve.py
bteve/eve.py
bteve/gameduino.py
bteve/gameduino_circuitpython.py
bteve/gameduino_spidriver.py
bteve/registers.py
bteve-0.2.2.dist-info/LICENSE
bteve-0.2.2.dist-info/METADATA
bteve-0.2.2.dist-info/WHEEL
bteve-0.2.2.dist-info/top_level.txt
bteve-0.2.2.dist-info/RECORD
