Metadata-Version: 2.1
Name: bteve
Version: 0.2.2
Summary: Interface to the Bridgetek EVE embedded GPUs
Home-page: http://gameduino.com
Author: James Bowman
Author-email: jamesb@excamera.com
License: GPL
Project-URL: Documentation, https://bteve.readthedocs.io/en/latest/
License-File: LICENSE
